{
  "_class": "shapeGroup",
  "clippingMaskMode": 0,
  "do_objectID": "D27518F4-3C9F-476A-A9A2-48C36BFA8DDA",
  "exportOptions": {
    "_class": "exportOptions",
    "exportFormats": [
    ],
    "includedLayerIds": [
    ],
    "layerOptions": 0,
    "shouldTrim": false
  },
  "frame": {
    "_class": "rect",
    "constrainProportions": false,
    "height": 6,
    "width": 70,
    "x": 75,
    "y": 127.1611652351683
  },
  "hasClickThrough": false,
  "hasClippingMask": false,
  "isFlippedHorizontal": false,
  "isFlippedVertical": false,
  "isLocked": false,
  "isVisible": true,
  "layerListExpandedType": 0,
  "layers": [
    {
      "class": "rectangle",
      "id": "BD3F41C3-6B6E-4C79-9716-535228C42FD1"
    }
  ],
  "name": "Text",
  "nameIsFixed": true,
  "resizingConstraint": 63,
  "resizingType": 0,
  "rotation": 0,
  "shouldBreakMaskChain": false,
  "style": {
    "sharedObjectID": "710D3369-D46D-4D28-A9CD-84B7339CD47D"
  },
  "windingRule": 1
}