{
  "_class": "shapeGroup",
  "clippingMaskMode": 0,
  "do_objectID": "B0D50E9C-1362-4416-923D-DF196C264D16",
  "exportOptions": {
    "_class": "exportOptions",
    "exportFormats": [
    ],
    "includedLayerIds": [
    ],
    "layerOptions": 0,
    "shouldTrim": false
  },
  "frame": {
    "_class": "rect",
    "constrainProportions": true,
    "height": 18,
    "width": 18,
    "x": 0,
    "y": 4
  },
  "hasClickThrough": false,
  "hasClippingMask": false,
  "isFlippedHorizontal": false,
  "isFlippedVertical": false,
  "isLocked": false,
  "isVisible": true,
  "layerListExpandedType": 0,
  "layers": [
    {
      "class": "oval",
      "id": "4BA431E5-3D28-4577-A296-9420ABC5F64F"
    }
  ],
  "name": "Oval",
  "nameIsFixed": false,
  "resizingConstraint": 63,
  "resizingType": 0,
  "rotation": 0,
  "shouldBreakMaskChain": false,
  "style": {
    "sharedObjectID": "B9EA25A7-9968-4421-A065-CA99AD600AF8"
  },
  "windingRule": 1
}