{
  "_class": "shapeGroup",
  "clippingMaskMode": 0,
  "do_objectID": "9CE2236C-DDC5-45F2-B138-674EF508DC37",
  "exportOptions": {
    "_class": "exportOptions",
    "exportFormats": [
    ],
    "includedLayerIds": [
    ],
    "layerOptions": 0,
    "shouldTrim": false
  },
  "frame": {
    "_class": "rect",
    "constrainProportions": false,
    "height": 168,
    "width": 44,
    "x": 62,
    "y": 24
  },
  "hasClickThrough": false,
  "hasClippingMask": false,
  "isFlippedHorizontal": false,
  "isFlippedVertical": false,
  "isLocked": false,
  "isVisible": true,
  "layerListExpandedType": 0,
  "layers": [
    {
      "class": "rectangle",
      "id": "67DAA63A-D1BF-495D-9472-D067EDFAB775"
    }
  ],
  "name": "Column",
  "nameIsFixed": true,
  "resizingConstraint": 63,
  "resizingType": 0,
  "rotation": 0,
  "shouldBreakMaskChain": false,
  "style": {
    "sharedObjectID": "B9EA25A7-9968-4421-A065-CA99AD600AF8"
  },
  "windingRule": 1
}