{
  "_class": "symbolInstance",
  "do_objectID": "2D36F57D-7B41-4A6B-8CCA-7FBF89FB713E",
  "exportOptions": {
    "_class": "exportOptions",
    "exportFormats": [
    ],
    "includedLayerIds": [
    ],
    "layerOptions": 0,
    "shouldTrim": false
  },
  "frame": {
    "_class": "rect",
    "constrainProportions": false,
    "height": 30,
    "width": 300,
    "x": 0,
    "y": 8
  },
  "horizontalSpacing": 0,
  "isFlippedHorizontal": false,
  "isFlippedVertical": true,
  "isLocked": false,
  "isVisible": true,
  "layerListExpandedType": 0,
  "masterInfluenceEdgeMaxXPadding": 1,
  "masterInfluenceEdgeMaxYPadding": 1,
  "masterInfluenceEdgeMinXPadding": 1,
  "masterInfluenceEdgeMinYPadding": 1,
  "name": "Connectors / Paths / Sad / Elbow",
  "nameIsFixed": true,
  "overrideValues": [
  ],
  "overrides": {
  },
  "resizingConstraint": 18,
  "resizingType": 0,
  "rotation": 0,
  "scale": 1,
  "shouldBreakMaskChain": false,
  "style": {
    "_class": "style",
    "endDecorationType": 0,
    "miterLimit": 10,
    "startDecorationType": 0
  },
  "symbolID": "A78962DA-CA7D-41BD-8055-9C6FC65C53C7",
  "verticalSpacing": 0
}