{
  "_class": "shapeGroup",
  "clippingMaskMode": 0,
  "do_objectID": "267A4350-B9C7-490F-968E-AA776DA06DCE",
  "exportOptions": {
    "_class": "exportOptions",
    "exportFormats": [
    ],
    "includedLayerIds": [
    ],
    "layerOptions": 0,
    "shouldTrim": false
  },
  "frame": {
    "_class": "rect",
    "constrainProportions": false,
    "height": 4,
    "width": 28,
    "x": 14,
    "y": 129
  },
  "hasClickThrough": false,
  "hasClippingMask": false,
  "isFlippedHorizontal": false,
  "isFlippedVertical": false,
  "isLocked": false,
  "isVisible": true,
  "layerListExpandedType": 0,
  "layers": [
    {
      "class": "rectangle",
      "id": "B24C6AC2-A0A9-40E0-9D76-6B60EBBBB761"
    }
  ],
  "name": "Text",
  "nameIsFixed": true,
  "resizingConstraint": 63,
  "resizingType": 0,
  "rotation": 0,
  "shouldBreakMaskChain": false,
  "style": {
    "sharedObjectID": "C040625B-12C5-4F30-9300-4FAB795AA96A"
  },
  "windingRule": 1
}