{
  "_class": "shapeGroup",
  "clippingMaskMode": 0,
  "do_objectID": "BD6CFE67-1ADE-4FB4-82AA-BE8E9FEAB7C4",
  "exportOptions": {
    "_class": "exportOptions",
    "exportFormats": [
    ],
    "includedLayerIds": [
    ],
    "layerOptions": 0,
    "shouldTrim": false
  },
  "frame": {
    "_class": "rect",
    "constrainProportions": false,
    "height": 4,
    "width": 28,
    "x": 164,
    "y": 163
  },
  "hasClickThrough": false,
  "hasClippingMask": false,
  "isFlippedHorizontal": false,
  "isFlippedVertical": false,
  "isLocked": false,
  "isVisible": true,
  "layerListExpandedType": 0,
  "layers": [
    {
      "class": "rectangle",
      "id": "1D5B9D9C-47AB-4193-B6D7-B0C4F70947DF"
    }
  ],
  "name": "Text",
  "nameIsFixed": true,
  "resizingConstraint": 63,
  "resizingType": 0,
  "rotation": 0,
  "shouldBreakMaskChain": false,
  "style": {
    "sharedObjectID": "B9EA25A7-9968-4421-A065-CA99AD600AF8"
  },
  "windingRule": 1
}