{
  "_class": "shapeGroup",
  "clippingMaskMode": 0,
  "do_objectID": "85E083AB-7404-4E07-84F8-505F39551394",
  "exportOptions": {
    "_class": "exportOptions",
    "exportFormats": [
    ],
    "includedLayerIds": [
    ],
    "layerOptions": 0,
    "shouldTrim": false
  },
  "frame": {
    "_class": "rect",
    "constrainProportions": false,
    "height": 14,
    "width": 4,
    "x": 24,
    "y": 8
  },
  "hasClickThrough": false,
  "hasClippingMask": false,
  "isFlippedHorizontal": false,
  "isFlippedVertical": false,
  "isLocked": false,
  "isVisible": true,
  "layerListExpandedType": 0,
  "layers": [
    {
      "class": "rectangle",
      "id": "21EDA16B-9DF5-4604-AE13-928501A9A82F"
    }
  ],
  "name": "Rectangle",
  "nameIsFixed": true,
  "resizingConstraint": 63,
  "resizingType": 0,
  "rotation": 0,
  "shouldBreakMaskChain": false,
  "style": {
    "sharedObjectID": "710D3369-D46D-4D28-A9CD-84B7339CD47D"
  },
  "windingRule": 1
}