{
  "_class": "shapeGroup",
  "clippingMaskMode": 0,
  "do_objectID": "B97EAAC4-96EF-41C3-8EEC-BCEA0964D948",
  "exportOptions": {
    "_class": "exportOptions",
    "exportFormats": [
    ],
    "includedLayerIds": [
    ],
    "layerOptions": 0,
    "shouldTrim": false
  },
  "frame": {
    "_class": "rect",
    "constrainProportions": false,
    "height": 30,
    "width": 40,
    "x": 42,
    "y": 142
  },
  "hasClickThrough": false,
  "hasClippingMask": false,
  "isFlippedHorizontal": false,
  "isFlippedVertical": false,
  "isLocked": false,
  "isVisible": true,
  "layerListExpandedType": 0,
  "layers": [
    {
      "class": "rectangle",
      "id": "DCD2951A-99C5-4024-A613-3C32639F5777"
    }
  ],
  "name": "Rectangle",
  "nameIsFixed": false,
  "resizingConstraint": 63,
  "resizingType": 0,
  "rotation": 0,
  "shouldBreakMaskChain": false,
  "style": {
    "sharedObjectID": "95DD792C-906E-479C-B3AB-B7401ACAA8C0"
  },
  "windingRule": 1
}