{
  "_class": "shapeGroup",
  "clippingMaskMode": 0,
  "do_objectID": "4FE4F349-D060-45FC-8411-E53ED2236150",
  "exportOptions": {
    "_class": "exportOptions",
    "exportFormats": [
    ],
    "includedLayerIds": [
    ],
    "layerOptions": 0,
    "shouldTrim": false
  },
  "frame": {
    "_class": "rect",
    "constrainProportions": false,
    "height": 22,
    "width": 4,
    "x": 17.99999999999977,
    "y": 4
  },
  "hasClickThrough": false,
  "hasClippingMask": false,
  "isFlippedHorizontal": false,
  "isFlippedVertical": false,
  "isLocked": false,
  "isVisible": true,
  "layerListExpandedType": 0,
  "layers": [
    {
      "class": "rectangle",
      "id": "8C7708BD-DDE8-4E07-8EBC-B3B6D63320EA"
    }
  ],
  "name": "Rectangle",
  "nameIsFixed": true,
  "resizingConstraint": 63,
  "resizingType": 0,
  "rotation": 0,
  "shouldBreakMaskChain": false,
  "style": {
    "sharedObjectID": "C040625B-12C5-4F30-9300-4FAB795AA96A"
  },
  "windingRule": 1
}