{
  "_class": "shapeGroup",
  "clippingMaskMode": 0,
  "do_objectID": "842E073F-906B-4664-909D-2C1161BD2FC4",
  "exportOptions": {
    "_class": "exportOptions",
    "exportFormats": [
    ],
    "includedLayerIds": [
    ],
    "layerOptions": 0,
    "shouldTrim": false
  },
  "frame": {
    "_class": "rect",
    "constrainProportions": false,
    "height": 6,
    "width": 88,
    "x": 18,
    "y": 84
  },
  "hasClickThrough": false,
  "hasClippingMask": false,
  "isFlippedHorizontal": false,
  "isFlippedVertical": false,
  "isLocked": false,
  "isVisible": true,
  "layerListExpandedType": 0,
  "layers": [
    {
      "class": "rectangle",
      "id": "333A6207-DEE6-4B04-9D32-A83C79B58E5D"
    }
  ],
  "name": "Rectangle",
  "nameIsFixed": true,
  "resizingConstraint": 63,
  "resizingType": 0,
  "rotation": 0,
  "shouldBreakMaskChain": false,
  "style": {
    "sharedObjectID": "95DD792C-906E-479C-B3AB-B7401ACAA8C0"
  },
  "windingRule": 1
}